sources/__init__.py
sources/colorengine.py
sources/configparser.py
sources/main.py
sources/tuxmodifier.py
sources/sprays/cape.svg
sources/sprays/eyepatch.svg
sources/sprays/glasses1.svg
sources/sprays/glasses11.svg
sources/sprays/helmet1.svg
sources/sprays/helmet2.svg
sources/sprays/helmet3.svg
sources/sprays/original_tux.svg
sources/sprays/shield.svg
sources/sprays/shield2.svg
sources/sprays/sword1.svg
sources/sprays/sword2.svg
sources/sprays/sword3.svg
sources/sprays/sword4.svg
sources/sprays/sword5.svg
sources/sprays/tattoo1.svg
tuxart-3.2.data/scripts/tuxart
tuxart-3.2.dist-info/METADATA
tuxart-3.2.dist-info/WHEEL
tuxart-3.2.dist-info/top_level.txt
tuxart-3.2.dist-info/RECORD
